bubble_plot/__init__.py
bubble_plot/bubble_plot.py
bubble_plot/utils.py
bubble_plot-0.3.4.data/scripts/bubble
bubble_plot-0.3.4.dist-info/LICENSE
bubble_plot-0.3.4.dist-info/METADATA
bubble_plot-0.3.4.dist-info/WHEEL
bubble_plot-0.3.4.dist-info/top_level.txt
bubble_plot-0.3.4.dist-info/RECORD
