Metadata-Version: 2.1
Name: bubble-plot
Version: 0.3.4
Summary: Bubble plot - data visualization package
Home-page: https://github.com/shirmeir/bubble_plot
Author: Shir Meir Lador
Author-email: meir.shir86@gmail.com
License: MIT
Platform: UNKNOWN
